[
  "ActionDsl",
  1,
  [
    "None"
  ],
  false,
  false,
  false,
  false,
  false,
  false,
  false,
  0,
  [
    "Block",
    [
      [
        "Command",
        [
          "SetPowerFilpSuppress",
          90
        ]
      ],
      [
        "Event",
        [
          "Wait",
          90,
          "ヒット判定",
          [
            "Block",
            [
              [
                "Command",
                [
                  "NotifyPowerflipEnd",
                  -18
                ]
              ]
            ]
          ]
        ]
      ],
      [
        "Command",
        [
          "ShowEffect",
          "オーラ演出",
          [
            "SpecifyEffectDirectly",
            "battle/effect/powerflip/psycho_reaper_meteor23/psycho_reaper_meteor23_powerflip_attack_special_player_one"
          ],
          -18,
          [
            "BacksideOfCharacter"
          ],
          [
            "SpecifyEffectLifetimeDirectly",
            90
          ],
          [
            "AB"
          ],
          0,
          0,
          0,
          true,
          true,
          [
            "Some",
            [
              {
                "max": 1,
                "min": 1
              }
            ]
          ]
        ]
      ],
      [
        "Event",
        [
          "CollisionOfBallAndEnemy",
          90,
          1,
          "*",
          0,
          [
            "Block",
            [
              [
                "Command",
                [
                  "HideEffect",
                  "オーラ演出"
                ]
              ],
              [
                "Command",
                [
                  "SetPowerFilpSuppress",
                  40
                ]
              ],
              [
                "Command",
                [
                  "RemoveEvent",
                  "ヒット判定"
                ]
              ],
              [
                "Event",
                [
                  "Wait",
                  38,
                  "*",
                  [
                    "Block",
                    [
                      [
                        "Command",
                        [
                          "NotifyPowerflipEnd",
                          -18
                        ]
                      ]
                    ]
                  ]
                ]
              ],
              [
                "Command",
                [
                  "CreateReferencePoint",
                  -18,
                  [
                    "AB"
                  ],
                  0,
                  0,
                  0,
                  false,
                  false,
                  [
                    "Single"
                  ],
                  40,
                  1,
                  [
                    "Block",
                    [
                      [
                        "Command",
                        [
                          "ShowEffect",
                          "特殊演出",
                          [
                            "SpecifyEffectDirectly",
                            "battle/effect/powerflip/psycho_reaper_meteor23/psycho_reaper_meteor23_powerflip_attack_special_one"
                          ],
                          1,
                          [
                            "ForesideOfCharacter"
                          ],
                          [
                            "SpecifyEffectLifetimeDirectly",
                            40
                          ],
                          [
                            "AB"
                          ],
                          0,
                          0,
                          0,
                          true,
                          true,
                          [
                            "Some",
                            [
                              {
                                "max": 4,
                                "min": 4
                              }
                            ]
                          ]
                        ]
                      ],
                      [
                        "Command",
                        [
                          "CreateHitArea",
                          "*",
                          1,
                          [
                            "AB"
                          ],
                          0,
                          0,
                          0,
                          false,
                          false,
                          [
                            "Circle",
                            [
                              {
                                "max": 200,
                                "min": 200
                              }
                            ]
                          ],
                          [
                            "Center"
                          ],
                          [
                            "Center"
                          ],
                          [
                            "Single"
                          ],
                          [
                            "SpecifyHitAreaLifetimeDirectly",
                            40
                          ],
                          [
                            "SpecifyMinHitIntervalDirectly",
                            7
                          ],
                          [
                            "Some",
                            [
                              {
                                "max": 3,
                                "min": 3
                              }
                            ]
                          ],
                          false,
                          true,
                          [
                            "None"
                          ],
                          2,
                          [
                            "Block",
                            null
                          ],
                          3,
                          4,
                          [
                            "Block",
                            [
                              [
                                "Command",
                                [
                                  "CreateNormalAttack",
                                  4,
                                  255,
                                  null,
                                  null,
                                  0,
                                  [
                                    {
                                      "max": 2.6666666666666665,
                                      "min": 2.6666666666666665
                                    }
                                  ],
                                  [
                                    {
                                      "max": 0,
                                      "min": 0
                                    }
                                  ],
                                  false,
                                  false,
                                  false,
                                  false,
                                  false,
                                  [
                                    {
                                      "max": 5,
                                      "min": 5
                                    }
                                  ],
                                  [
                                    {
                                      "max": 5.6000000000000005,
                                      "min": 5.6000000000000005
                                    }
                                  ],
                                  [
                                    "Fine"
                                  ],
                                  true
                                ]
                              ],
                              [
                                "Command",
                                [
                                  "ShakeCamera",
                                  1
                                ]
                              ]
                            ]
                          ],
                          0,
                          0,
                          [
                            "None"
                          ]
                        ]
                      ]
                    ]
                  ]
                ]
              ]
            ]
          ]
        ]
      ]
    ]
  ]
]
