{
  "xm20_white_tiger": {
    "0": [
      [
        "0",
        "おう、元気そうじゃねぇか。"
      ]
    ],
    "1": [
      [
        "0",
        "……俺か？見りゃわかんだろ？"
      ]
    ],
    "2": [
      [
        "0",
        "手伝いだよ。クリスマスの。"
      ]
    ],
    "3": [
      [
        "0",
        "笑ってんじゃねえよ。お前も手伝えや！"
      ]
    ]
  },
  "xm20_dryad": {
    "0": [
      [
        "0",
        "今年もみんな、キラキラ♪"
      ]
    ],
    "1": [
      [
        "0",
        "みんな楽しそう、チャルアうれしい！"
      ]
    ],
    "2": [
      [
        "0",
        "来年も楽しくなりますように！"
      ]
    ]
  },
  "ny21_cat_fighter": {
    "0": [
      [
        "0",
        "あけましておめでとうなのにゃ！"
      ]
    ],
    "1": [
      [
        "0",
        "今年も１年、よろしくなのにゃ。"
      ]
    ],
    "2": [
      [
        "0",
        "もうお願い事は済んだかにゃ？"
      ]
    ],
    "3": [
      [
        "0",
        "わ、わたしのお願い事？ひ、秘密なのにゃー！"
      ]
    ]
  },
  "anv4_alk": {
    "0": [
      [
        "0",
        "みんな、来てくれてありがとう！"
      ]
    ],
    "1": [
      [
        "0",
        "君達がいてくれたから、ここまで来れたんだ"
      ]
    ],
    "2": [
      [
        "0",
        "大丈夫。たとえ旅路が違っても"
      ]
    ],
    "3": [
      [
        "0",
        "僕達は君達と共に在るよ"
      ]
    ]
  },
  "anv4_stella": {
    "0": [
      [
        "0",
        "４年間、\nたくさんお宝をもらいました"
      ]
    ],
    "1": [
      [
        "0",
        "あなたのお宝は\n見つかりましたか？"
      ]
    ],
    "2": [
      [
        "0",
        "これからも、\n皆さんと一緒です"
      ]
    ],
    "3": [
      [
        "0",
        "星見の街はあなたを歓迎します"
      ]
    ]
  },
  "anv4_light": {
    "0": [
      [
        "0",
        "来てくれたか、ありがとう！"
      ]
    ],
    "1": [
      [
        "0",
        "共に過ごしてきた時間こそが、\n私の宝物だ"
      ]
    ],
    "2": [
      [
        "0",
        "この先も、我々は歩いていく"
      ]
    ],
    "3": [
      [
        "0",
        "みな、また会おう！"
      ]
    ]
  },
  "anv4_light_adventurer": {
    "0": [
      [
        "0",
        "やあみな、元気にしているか？"
      ]
    ],
    "1": [
      [
        "0",
        "このような姿で驚かせただろうか？"
      ]
    ],
    "2": [
      [
        "0",
        "随分と小さくなってしまったが"
      ]
    ],
    "3": [
      [
        "0",
        "私はこれからも、君達と共に在る！"
      ]
    ]
  },
  "anv3_alk": {
    "0": [
      [
        "0",
        "会いにきてくれてありがとう！"
      ]
    ],
    "1": [
      [
        "0",
        "３年かあ、いろんなことがあったけど"
      ]
    ],
    "2": [
      [
        "0",
        "僕は進んでいくよ。"
      ]
    ],
    "3": [
      [
        "0",
        "また会おうね！"
      ]
    ]
  },
  "anv3_stella": {
    "0": [
      [
        "0",
        "今年で皆さんと\n出会ってから３年です。"
      ]
    ],
    "1": [
      [
        "0",
        "改めて、\nいつもありがとうございます。"
      ]
    ],
    "2": [
      [
        "0",
        "これからも皆さんと\n一緒に過ごしたいです。"
      ]
    ],
    "3": [
      [
        "0",
        "よろしくお願いします。"
      ]
    ]
  },
  "anv3_light": {
    "0": [
      [
        "0",
        "来てくれたのだな！待っていたぞ！"
      ]
    ],
    "1": [
      [
        "0",
        "みなと共に過ごして\n３年がたったのだな。"
      ]
    ],
    "2": [
      [
        "0",
        "これからも共に進もう。"
      ]
    ],
    "3": [
      [
        "0",
        "よろしく頼む。"
      ]
    ]
  },
  "anv2_alk": {
    "0": [
      [
        "0",
        "来てくれたんだね！"
      ]
    ],
    "1": [
      [
        "0",
        "お祝いの準備はできてるよ！"
      ]
    ],
    "2": [
      [
        "0",
        "改めて、いつもありがとう。"
      ]
    ],
    "3": [
      [
        "0",
        "これからも一緒に過ごそうね。"
      ]
    ]
  },
  "anv2_stella": {
    "0": [
      [
        "0",
        "２周年おめでとうございます。"
      ]
    ],
    "1": [
      [
        "0",
        "今年もみなさんと\nお祝いできて嬉しいです。"
      ]
    ],
    "2": [
      [
        "0",
        "楽しい時間を過ごしましょう。"
      ]
    ],
    "3": [
      [
        "0",
        "これからもよろしくお願いします。"
      ]
    ]
  },
  "anv2_light": {
    "0": [
      [
        "0",
        "みんなが来るのを待っていたぞ！"
      ]
    ],
    "1": [
      [
        "0",
        "こうして祝えるのも、\n君達の応援あってこそだ。"
      ]
    ],
    "2": [
      [
        "0",
        "ありがとう、\nこれからもよろしく頼む。"
      ]
    ],
    "3": [
      [
        "0",
        "さて、私も気合を入れねばな。"
      ]
    ]
  },
  "anv2_dryad": {
    "0": [
      [
        "0",
        "チャルア、みんなとあえてうれしい♪"
      ]
    ],
    "1": [
      [
        "0",
        "この前、ステラからインタビューされたの！"
      ]
    ],
    "2": [
      [
        "0",
        "とっても楽しかった～。"
      ]
    ],
    "3": [
      [
        "0",
        "お祭り、１０日後だよ♪"
      ]
    ]
  },
  "anv2_pirates_girl": {
    "0": [
      [
        "0",
        "あと９日！待ってたよ！"
      ]
    ],
    "1": [
      [
        "0",
        "もう２年かあ。あっという間だったけどさ。"
      ]
    ],
    "2": [
      [
        "0",
        "海でも空でも、派手に海賊するよ？"
      ]
    ],
    "3": [
      [
        "0",
        "もちろん、ついてくるでしょ？"
      ]
    ]
  },
  "anv2_fox_oracle": {
    "0": [
      [
        "0",
        "遂に、２周年じゃぞーーー！！"
      ]
    ],
    "1": [
      [
        "0",
        "ふっふっふ、１周年の時から数えていたんじゃよ！"
      ]
    ],
    "2": [
      [
        "0",
        "はわーーー！祝いのアルク飯じゃ～～。"
      ]
    ],
    "3": [
      [
        "0",
        "８日後まで、遊び呆けるぞ～！"
      ]
    ]
  },
  "anv2_resistance_princess": {
    "0": [
      [
        "0",
        "皆さん、お待ちしていました。"
      ]
    ],
    "1": [
      [
        "0",
        "いよいよ７日後ですね。楽しみましょう。"
      ]
    ],
    "2": [
      [
        "0",
        "共に歩める事、光栄に思います。"
      ]
    ],
    "3": [
      [
        "0",
        "……多少は羽目を外してもいいですよね？"
      ]
    ]
  },
  "anv2_guildknight_leader": {
    "0": [
      [
        "0",
        "あと６日で２周年だってさ。早いよねえ。"
      ]
    ],
    "1": [
      [
        "0",
        "よーし、祝いにこのアメちゃんをやろう。"
      ]
    ],
    "2": [
      [
        "0",
        "ははは。意外といけるでしょ？"
      ]
    ],
    "3": [
      [
        "0",
        "ま。改めて、よろしくな。"
      ]
    ]
  },
  "anv2_horn_leader": {
    "0": [
      [
        "0",
        "お前達が来るのを待っていました。"
      ]
    ],
    "1": [
      [
        "0",
        "２周年の祝いだと聞いています。"
      ]
    ],
    "2": [
      [
        "0",
        "もちろん、勇者の赤いスープもあります。"
      ]
    ],
    "3": [
      [
        "0",
        "あと５日。共に楽しみましょう。"
      ]
    ]
  },
  "anv2_npc_nova": {
    "0": [
      [
        "0",
        "来てくれてありがとう！"
      ]
    ],
    "1": [
      [
        "0",
        "一緒にお祝いできて、嬉しいよ。"
      ]
    ],
    "2": [
      [
        "0",
        "僕もやっとこの街に馴染めてきたかな？"
      ]
    ],
    "3": [
      [
        "0",
        "あと４日だ。また遊んでほしいね。"
      ]
    ]
  },
  "anv2_psychic_yuki": {
    "0": [
      [
        "0",
        "もう２周年なんだ。すごいな……"
      ]
    ],
    "1": [
      [
        "0",
        "えっ、もう３日後なの？"
      ]
    ],
    "2": [
      [
        "0",
        "えっとえっと～……こういうの慣れてなくて。"
      ]
    ],
    "3": [
      [
        "0",
        "こ、これからもよろしくね！"
      ]
    ]
  },
  "anv2_psychic_shouta": {
    "0": [
      [
        "0",
        "お！やっと来たな！"
      ]
    ],
    "1": [
      [
        "0",
        "やべーな。２周年とか！もう明後日だろ？"
      ]
    ],
    "2": [
      [
        "0",
        "向こうの街なら、俺が案内してやるよ！"
      ]
    ],
    "3": [
      [
        "0",
        "へへっ。遊びに関しちゃ任せてくれよな。"
      ]
    ]
  },
  "anv2_psychic_nao": {
    "0": [
      [
        "0",
        "２周年おっめでとーう！いよいよ明日だよ！"
      ]
    ],
    "1": [
      [
        "0",
        "えっ！お兄ちゃん達まだ来てないの！？"
      ]
    ],
    "2": [
      [
        "0",
        "任せて！ナオが呼んでくるから。"
      ]
    ],
    "3": [
      [
        "0",
        "これからはナオも一緒だよ！"
      ]
    ]
  },
  "anv1half_alk": {
    "0": [
      [
        "0",
        "みんなお祝いだよ！"
      ]
    ],
    "1": [
      [
        "0",
        "やあ、１年と半分。色々あったよね。"
      ]
    ],
    "2": [
      [
        "0",
        "これからもだろうけど、きっと大丈夫！"
      ]
    ],
    "3": [
      [
        "0",
        "特製ケーキ作ったから、楽しみにね～。"
      ]
    ]
  },
  "anv1half_stella": {
    "0": [
      [
        "0",
        "皆さんとお会いして１年と半分です。"
      ]
    ],
    "1": [
      [
        "0",
        "ソーニャさんとのダンス頑張りました。"
      ]
    ],
    "2": [
      [
        "0",
        "楽しみにしていてください。"
      ]
    ],
    "3": [
      [
        "0",
        "これからもよろしくお願いします。"
      ]
    ]
  },
  "anv1half_light2": {
    "0": [
      [
        "0",
        "みんな、来てくれたのか！"
      ]
    ],
    "1": [
      [
        "0",
        "どうも最近おもちゃに\nされる事が多いが……"
      ]
    ],
    "2": [
      [
        "0",
        "まあいいさ。\n君達が笑顔でいられるならな。"
      ]
    ],
    "3": [
      [
        "0",
        "よろしく頼むぞ。勇者達よ！"
      ]
    ]
  },
  "anv1half_lich": {
    "0": [
      [
        "0",
        "ほっほ、いつもありがとうのう！"
      ]
    ],
    "1": [
      [
        "0",
        "お前さんがたの活躍、聞いておるぞ。"
      ]
    ],
    "2": [
      [
        "0",
        "これからもよろしく頼むぞ？"
      ]
    ],
    "3": [
      [
        "0",
        "たまには顔を見せてくれい！"
      ]
    ]
  },
  "anv1half_white_tiger": {
    "0": [
      [
        "0",
        "おう、元気か？"
      ]
    ],
    "1": [
      [
        "0",
        "長い付き合いになってきたよな。"
      ]
    ],
    "2": [
      [
        "0",
        "っへ、今更なにを言うって事もねえけどよ。"
      ]
    ],
    "3": [
      [
        "0",
        "ま、これからも頼むぜ？"
      ]
    ]
  },
  "anv1half_mermaid": {
    "0": [
      [
        "0",
        "１年と半分おーめでとー♪"
      ]
    ],
    "1": [
      [
        "0",
        "えっ？まだ早い？いいじゃん別にー！"
      ]
    ],
    "2": [
      [
        "0",
        "これからも、色んな冒険一緒しようね！"
      ]
    ],
    "3": [
      [
        "0",
        "はー、明日はどこ行こっかなー♪"
      ]
    ]
  },
  "anv1half_wolf_assasin": {
    "0": [
      [
        "0",
        "祝いの席だそうだな、おめでとう。"
      ]
    ],
    "1": [
      [
        "0",
        "華やかな場は得意ではないが……"
      ]
    ],
    "2": [
      [
        "0",
        "嫌いという訳でもない……"
      ]
    ],
    "3": [
      [
        "0",
        "無愛想？……許せ、これが限界だ。"
      ]
    ]
  },
  "anv1half_rec_android": {
    "0": [
      [
        "0",
        "ハハハ、ハッピーアニバーサリー！"
      ]
    ],
    "1": [
      [
        "0",
        "どうだい、元気かな！？"
      ]
    ],
    "2": [
      [
        "0",
        "長い旅路の一息……うむ、悪くないな。"
      ]
    ],
    "3": [
      [
        "0",
        "これからも末永く、よろしく頼むよ。"
      ]
    ]
  },
  "anv1half_onmyoji_boy": {
    "0": [
      [
        "0",
        "１年と半分、変わらぬご愛顧感謝いたします。"
      ]
    ],
    "1": [
      [
        "0",
        "僭越ながら、祝辞を述べさせていただきます。"
      ]
    ],
    "2": [
      [
        "0",
        "波乱万丈の道のりではありますが"
      ]
    ],
    "3": [
      [
        "0",
        "何卒今後ともご贔屓にお願いいたします。"
      ]
    ]
  },
  "anv1half_resistance_princess": {
    "0": [
      [
        "0",
        "謹んで、お祝い申し上げます。"
      ]
    ],
    "1": [
      [
        "0",
        "ふふふ、これでも王族ですからね？"
      ]
    ],
    "2": [
      [
        "0",
        "あなた達と共に在る事が、私の誇りです。"
      ]
    ],
    "3": [
      [
        "0",
        "これからよろしくお願いしますね！"
      ]
    ]
  },
  "anv1half_devil_leader": {
    "0": [
      [
        "0",
        "招待、感謝する。"
      ]
    ],
    "1": [
      [
        "0",
        "ふっ……相変わらずのようだな。"
      ]
    ],
    "2": [
      [
        "0",
        "確かに、時には休息も必要だ。"
      ]
    ],
    "3": [
      [
        "0",
        "今宵は付き合ってもらうぞ？"
      ]
    ]
  },
  "anv1half_elf_princess": {
    "0": [
      [
        "0",
        "皆の者、大義である。"
      ]
    ],
    "1": [
      [
        "0",
        "前祝いだ。存分に愉しむがいい。"
      ]
    ],
    "2": [
      [
        "0",
        "月日は疾く過ぎゆくもの。"
      ]
    ],
    "3": [
      [
        "0",
        "今日を共に過ごせる事、分かち合おうぞ？"
      ]
    ]
  },
  "anv1half_light": {
    "0": [
      [
        "0",
        "もうまもなく、本祝いだな！"
      ]
    ],
    "1": [
      [
        "0",
        "改めて、ありがとう！そしておめでとう！"
      ]
    ],
    "2": [
      [
        "0",
        "これからも我々の行く末を見守ってくれ。"
      ]
    ],
    "3": [
      [
        "0",
        "皆の日々に、幸多からん事を！"
      ]
    ]
  },
  "anv1_alk": {
    "0": [
      [
        "0",
        "みんな、いつもありがとう！"
      ]
    ],
    "1": [
      [
        "0",
        "いやぁ１年経っちゃったね～。"
      ]
    ],
    "2": [
      [
        "0",
        "まだまだ僕らの冒険は続くよ。"
      ]
    ],
    "3": [
      [
        "0",
        "これからもよろしくね！"
      ]
    ]
  },
  "anv1_stella": {
    "0": [
      [
        "0",
        "おめでとうございます。"
      ]
    ],
    "1": [
      [
        "0",
        "皆さんとお会いして１年です。"
      ]
    ],
    "2": [
      [
        "0",
        "とてもすてきな時間でした。"
      ]
    ],
    "3": [
      [
        "0",
        "これからも、よろしくお願いします。"
      ]
    ]
  },
  "anv1_light": {
    "0": [
      [
        "0",
        "みな、遂に１周年だぞ！"
      ]
    ],
    "1": [
      [
        "0",
        "これも君達の応援のお陰だ。"
      ]
    ],
    "2": [
      [
        "0",
        "これからも力を貸して欲しい。"
      ]
    ],
    "3": [
      [
        "0",
        "よろしく頼むぞ。勇者達よ！"
      ]
    ]
  },
  "anv1_dryad": {
    "0": [
      [
        "0",
        "１周年、後１０日です♪"
      ]
    ],
    "1": [
      [
        "0",
        "一緒にお祝い、してくれる？"
      ]
    ],
    "2": [
      [
        "0",
        "また遊んでね～。"
      ]
    ]
  },
  "anv1_white_tiger": {
    "0": [
      [
        "0",
        "っへ、浮かれてやがんな？"
      ]
    ],
    "1": [
      [
        "0",
        "祭りはまぁ嫌いじゃねえけどよ。"
      ]
    ],
    "2": [
      [
        "0",
        "後９日、ちゃんと来いよ？"
      ]
    ]
  },
  "anv1_pirates_girl": {
    "0": [
      [
        "0",
        "いつもありがとね！"
      ]
    ],
    "1": [
      [
        "0",
        "後８日で１年、あっという間よね～。"
      ]
    ],
    "2": [
      [
        "0",
        "盛り上げていくからねー！"
      ]
    ]
  },
  "anv1_mermaid": {
    "0": [
      [
        "0",
        "やっほー！元気？"
      ]
    ],
    "1": [
      [
        "0",
        "毎日ちゃんと来てくれてる？"
      ]
    ],
    "2": [
      [
        "0",
        "後７日、忘れず来てよ？絶対よ！？"
      ]
    ]
  },
  "anv1_outlaw_panther": {
    "0": [
      [
        "0",
        "こんちゃっす、毎日ありがとっす！"
      ]
    ],
    "1": [
      [
        "0",
        "後６日でお祭りっすね。楽しみっす！"
      ]
    ],
    "2": [
      [
        "0",
        "予定、ちゃんと空けとくっすよ？"
      ]
    ]
  },
  "anv1_wolf_swordsman": {
    "0": [
      [
        "0",
        "１周年、誠にめでたいな。"
      ]
    ],
    "1": [
      [
        "0",
        "これもひとえに君達のお陰だろう。"
      ]
    ],
    "2": [
      [
        "0",
        "本祭まで後５日、忘れぬようにな！"
      ]
    ]
  },
  "anv1_sing_android": {
    "0": [
      [
        "0",
        "今日もきてくれてありがとう！"
      ]
    ],
    "1": [
      [
        "0",
        "後４日、ワクワクしちゃうね♪"
      ]
    ],
    "2": [
      [
        "0",
        "これからも一緒だよっ。"
      ]
    ]
  },
  "anv1_onmyoji_boy": {
    "0": [
      [
        "0",
        "祝辞の儀、承りました。"
      ]
    ],
    "1": [
      [
        "0",
        "これからも皆様にご多幸を。"
      ]
    ],
    "2": [
      [
        "0",
        "３日後の本祭、是非お越しください。"
      ]
    ]
  },
  "anv1_samurai": {
    "0": [
      [
        "0",
        "平素のご愛顧、誠に感謝いたします。"
      ]
    ],
    "1": [
      [
        "0",
        "前祝いも後２日です。"
      ]
    ],
    "2": [
      [
        "0",
        "どうぞこれからもご贔屓に♪"
      ]
    ]
  },
  "anv1_fox_oracle": {
    "0": [
      [
        "0",
        "皆の者ー！準備はよいかー！？"
      ]
    ],
    "1": [
      [
        "0",
        "遂に明日は１周年じゃぞー♪"
      ]
    ],
    "2": [
      [
        "0",
        "お主達の応援、これからも頼むぞ！"
      ]
    ]
  }
}
